vasptools/__init__.py
vasptools/api.py
vasptools/atom_selector.py
vasptools/chg.py
vasptools/chgcar.py
vasptools/doscar.py
vasptools/ext_types.py
vasptools/format_parser.py
vasptools/format_string.py
vasptools/incar.py
vasptools/kpoints.py
vasptools/outcar.py
vasptools/poscar.py
vasptools/potcar.py
vasptools/template.py
vasptools/units.py
vasptools/utils.py
vasptools/vasprun.py
vasptools/wavecar.py
vasptools/cli/__init__.py
vasptools/cli/check.py
vasptools/cli/complete.py
vasptools/cli/vasptools_cli.py
vasptools/cli/vasptools_handlers.py
vasptools-0.6.1.dist-info/LICENSE
vasptools-0.6.1.dist-info/METADATA
vasptools-0.6.1.dist-info/WHEEL
vasptools-0.6.1.dist-info/entry_points.txt
vasptools-0.6.1.dist-info/top_level.txt
vasptools-0.6.1.dist-info/RECORD
