Metadata-Version: 2.1
Name: vasptools
Version: 0.6.1
Summary: tool collection for parsing vasp inputs & outputs
Home-page: https://github.com/atomse/vasptools
Author: Sky Zhang
Author-email: sky.atomse@gmail.com
Maintainer: Sky Zhang
Maintainer-email: sky.atomse@gmail.com
License: MIT License
Platform: Linux
Platform: Darwin
Classifier: Development Status :: 4 - Beta
Classifier: Operating System :: MacOS
Classifier: Operating System :: POSIX
Classifier: Intended Audience :: Science/Research
Classifier: License :: OSI Approved :: MIT License
Classifier: Programming Language :: Python
Classifier: Programming Language :: Python :: Implementation
Classifier: Programming Language :: Python :: 3
Classifier: Programming Language :: Python :: 3.5
Classifier: Programming Language :: Python :: 3.6
Classifier: Programming Language :: Python :: 3.7
Requires-Python: >=3
Requires-Dist: numpy
Requires-Dist: pandas
Requires-Dist: sh (>=1.10.0)
Requires-Dist: argcomplete
Requires-Dist: ase
Requires-Dist: lxml
Requires-Dist: json-tricks
Provides-Extra: curate
Requires-Dist: graphviz ; extra == 'curate'
Provides-Extra: docs
Requires-Dist: sphinx ; extra == 'docs'
Requires-Dist: sphinxcontrib-programoutput ; extra == 'docs'
Requires-Dist: sphinx-rtd-theme ; extra == 'docs'
Requires-Dist: numpydoc ; extra == 'docs'
Provides-Extra: tests
Requires-Dist: pytest (>=4.0) ; extra == 'tests'
Requires-Dist: pytest-cov ; extra == 'tests'
